{
    "name": "park", 
    "text": "Park", 
    "blank_option": true, 
    "prefix": "properties", 
    "values": [
        {
            "default": false, 
            "enabled": true, 
            "properties": null, 
            "label": "ABLI"
        }, 
        {
            "default": false, 
            "enabled": true, 
            "properties": null, 
            "label": "ACAD"
        }, 
        {
            "default": false, 
            "enabled": true, 
            "properties": null, 
            "label": "ADAM"
        }, 
        {
            "default": false, 
            "enabled": true, 
            "properties": null, 
            "label": "AFBG"
        }, 
        {
            "default": false, 
            "enabled": true, 
            "properties": null, 
            "label": "AGFO"
        }, 
        {
            "default": false, 
            "enabled": true, 
            "properties": null, 
            "label": "ALAG"
        }, 
        {
            "default": false, 
            "enabled": true, 
            "properties": null, 
            "label": "ALFL"
        }, 
        {
            "default": false, 
            "enabled": true, 
            "properties": null, 
            "label": "ALPO"
        }, 
        {
            "default": false, 
            "enabled": true, 
            "properties": null, 
            "label": "AMIS"
        }, 
        {
            "default": false, 
            "enabled": true, 
            "properties": null, 
            "label": "AMME"
        }, 
        {
            "default": false, 
            "enabled": true, 
            "properties": null, 
            "label": "ANAC"
        }, 
        {
            "default": false, 
            "enabled": true, 
            "properties": null, 
            "label": "ANDE"
        }, 
        {
            "default": false, 
            "enabled": true, 
            "properties": null, 
            "label": "ANIA"
        }, 
        {
            "default": false, 
            "enabled": true, 
            "properties": null, 
            "label": "ANJO"
        }, 
        {
            "default": false, 
            "enabled": true, 
            "properties": null, 
            "label": "ANTI"
        }, 
        {
            "default": false, 
            "enabled": true, 
            "properties": null, 
            "label": "APCO"
        }, 
        {
            "default": false, 
            "enabled": true, 
            "properties": null, 
            "label": "APIS"
        }, 
        {
            "default": false, 
            "enabled": true, 
            "properties": null, 
            "label": "APPA"
        }, 
        {
            "default": false, 
            "enabled": true, 
            "properties": null, 
            "label": "ARCH"
        }, 
        {
            "default": false, 
            "enabled": true, 
            "properties": null, 
            "label": "ARHO"
        }, 
        {
            "default": false, 
            "enabled": true, 
            "properties": null, 
            "label": "ARPO"
        }, 
        {
            "default": false, 
            "enabled": true, 
            "properties": null, 
            "label": "ASIS"
        }, 
        {
            "default": false, 
            "enabled": true, 
            "properties": null, 
            "label": "AZRU"
        }, 
        {
            "default": false, 
            "enabled": true, 
            "properties": null, 
            "label": "BADL"
        }, 
        {
            "default": false, 
            "enabled": true, 
            "properties": null, 
            "label": "BAND"
        }, 
        {
            "default": false, 
            "enabled": true, 
            "properties": null, 
            "label": "BAWA"
        }, 
        {
            "default": false, 
            "enabled": true, 
            "properties": null, 
            "label": "BELA"
        }, 
        {
            "default": false, 
            "enabled": true, 
            "properties": null, 
            "label": "BEOL"
        }, 
        {
            "default": false, 
            "enabled": true, 
            "properties": null, 
            "label": "BIBE"
        }, 
        {
            "default": false, 
            "enabled": true, 
            "properties": null, 
            "label": "BICA"
        }, 
        {
            "default": false, 
            "enabled": true, 
            "properties": null, 
            "label": "BICY"
        }, 
        {
            "default": false, 
            "enabled": true, 
            "properties": null, 
            "label": "BIHO"
        }, 
        {
            "default": false, 
            "enabled": true, 
            "properties": null, 
            "label": "BISC"
        }, 
        {
            "default": false, 
            "enabled": true, 
            "properties": null, 
            "label": "BISO"
        }, 
        {
            "default": false, 
            "enabled": true, 
            "properties": null, 
            "label": "BITH"
        }, 
        {
            "default": false, 
            "enabled": true, 
            "properties": null, 
            "label": "BLCA"
        }, 
        {
            "default": false, 
            "enabled": true, 
            "properties": null, 
            "label": "BLRI"
        }, 
        {
            "default": false, 
            "enabled": true, 
            "properties": null, 
            "label": "BLUE"
        }, 
        {
            "default": false, 
            "enabled": true, 
            "properties": null, 
            "label": "BOAF"
        }, 
        {
            "default": false, 
            "enabled": true, 
            "properties": null, 
            "label": "BOHA"
        }, 
        {
            "default": false, 
            "enabled": true, 
            "properties": null, 
            "label": "BOST"
        }, 
        {
            "default": false, 
            "enabled": true, 
            "properties": null, 
            "label": "BOWA"
        }, 
        {
            "default": false, 
            "enabled": true, 
            "properties": null, 
            "label": "BRCA"
        }, 
        {
            "default": false, 
            "enabled": true, 
            "properties": null, 
            "label": "BRCR"
        }, 
        {
            "default": false, 
            "enabled": true, 
            "properties": null, 
            "label": "BRVB"
        }, 
        {
            "default": false, 
            "enabled": true, 
            "properties": null, 
            "label": "BUFF"
        }, 
        {
            "default": false, 
            "enabled": true, 
            "properties": null, 
            "label": "BUIS"
        }, 
        {
            "default": false, 
            "enabled": true, 
            "properties": null, 
            "label": "CABR"
        }, 
        {
            "default": false, 
            "enabled": true, 
            "properties": null, 
            "label": "CACH"
        }, 
        {
            "default": false, 
            "enabled": true, 
            "properties": null, 
            "label": "CACL"
        }, 
        {
            "default": false, 
            "enabled": true, 
            "properties": null, 
            "label": "CACO"
        }, 
        {
            "default": false, 
            "enabled": true, 
            "properties": null, 
            "label": "CAGR"
        }, 
        {
            "default": false, 
            "enabled": true, 
            "properties": null, 
            "label": "CAHA"
        }, 
        {
            "default": false, 
            "enabled": true, 
            "properties": null, 
            "label": "CAKR"
        }, 
        {
            "default": false, 
            "enabled": true, 
            "properties": null, 
            "label": "CALO"
        }, 
        {
            "default": false, 
            "enabled": true, 
            "properties": null, 
            "label": "CANA"
        }, 
        {
            "default": false, 
            "enabled": true, 
            "properties": null, 
            "label": "CANY"
        }, 
        {
            "default": false, 
            "enabled": true, 
            "properties": null, 
            "label": "CARE"
        }, 
        {
            "default": false, 
            "enabled": true, 
            "properties": null, 
            "label": "CARI"
        }, 
        {
            "default": false, 
            "enabled": true, 
            "properties": null, 
            "label": "CARL"
        }, 
        {
            "default": false, 
            "enabled": true, 
            "properties": null, 
            "label": "CASA"
        }, 
        {
            "default": false, 
            "enabled": true, 
            "properties": null, 
            "label": "CATO"
        }, 
        {
            "default": false, 
            "enabled": true, 
            "properties": null, 
            "label": "CAVE"
        }, 
        {
            "default": false, 
            "enabled": true, 
            "properties": null, 
            "label": "CAVO"
        }, 
        {
            "default": false, 
            "enabled": true, 
            "properties": null, 
            "label": "CAWO"
        }, 
        {
            "default": false, 
            "enabled": true, 
            "properties": null, 
            "label": "CEBE"
        }, 
        {
            "default": false, 
            "enabled": true, 
            "properties": null, 
            "label": "CEBR"
        }, 
        {
            "default": false, 
            "enabled": true, 
            "properties": null, 
            "label": "CHAM"
        }, 
        {
            "default": false, 
            "enabled": true, 
            "properties": null, 
            "label": "CHAT"
        }, 
        {
            "default": false, 
            "enabled": true, 
            "properties": null, 
            "label": "CHCH"
        }, 
        {
            "default": false, 
            "enabled": true, 
            "properties": null, 
            "label": "CHCU"
        }, 
        {
            "default": false, 
            "enabled": true, 
            "properties": null, 
            "label": "CHIC"
        }, 
        {
            "default": false, 
            "enabled": true, 
            "properties": null, 
            "label": "CHIR"
        }, 
        {
            "default": false, 
            "enabled": true, 
            "properties": null, 
            "label": "CHIS"
        }, 
        {
            "default": false, 
            "enabled": true, 
            "properties": null, 
            "label": "CHOH"
        }, 
        {
            "default": false, 
            "enabled": true, 
            "properties": null, 
            "label": "CHPI"
        }, 
        {
            "default": false, 
            "enabled": true, 
            "properties": null, 
            "label": "CHRI"
        }, 
        {
            "default": false, 
            "enabled": true, 
            "properties": null, 
            "label": "CHSC"
        }, 
        {
            "default": false, 
            "enabled": true, 
            "properties": null, 
            "label": "CIRO"
        }, 
        {
            "default": false, 
            "enabled": true, 
            "properties": null, 
            "label": "CLBA"
        }, 
        {
            "default": false, 
            "enabled": true, 
            "properties": null, 
            "label": "COGA"
        }, 
        {
            "default": false, 
            "enabled": true, 
            "properties": null, 
            "label": "COLM"
        }, 
        {
            "default": false, 
            "enabled": true, 
            "properties": null, 
            "label": "COLO"
        }, 
        {
            "default": false, 
            "enabled": true, 
            "properties": null, 
            "label": "CONG"
        }, 
        {
            "default": false, 
            "enabled": true, 
            "properties": null, 
            "label": "CORO"
        }, 
        {
            "default": false, 
            "enabled": true, 
            "properties": null, 
            "label": "COWP"
        }, 
        {
            "default": false, 
            "enabled": true, 
            "properties": null, 
            "label": "CRLA"
        }, 
        {
            "default": false, 
            "enabled": true, 
            "properties": null, 
            "label": "CRMO"
        }, 
        {
            "default": false, 
            "enabled": true, 
            "properties": null, 
            "label": "CUGA"
        }, 
        {
            "default": false, 
            "enabled": true, 
            "properties": null, 
            "label": "CUIS"
        }, 
        {
            "default": false, 
            "enabled": true, 
            "properties": null, 
            "label": "CURE"
        }, 
        {
            "default": false, 
            "enabled": true, 
            "properties": null, 
            "label": "CUVA"
        }, 
        {
            "default": false, 
            "enabled": true, 
            "properties": null, 
            "label": "DAAV"
        }, 
        {
            "default": false, 
            "enabled": true, 
            "properties": null, 
            "label": "DENA"
        }, 
        {
            "default": false, 
            "enabled": true, 
            "properties": null, 
            "label": "DEPO"
        }, 
        {
            "default": false, 
            "enabled": true, 
            "properties": null, 
            "label": "DESO"
        }, 
        {
            "default": false, 
            "enabled": true, 
            "properties": null, 
            "label": "DETO"
        }, 
        {
            "default": false, 
            "enabled": true, 
            "properties": null, 
            "label": "DEVA"
        }, 
        {
            "default": false, 
            "enabled": true, 
            "properties": null, 
            "label": "DEWA"
        }, 
        {
            "default": false, 
            "enabled": true, 
            "properties": null, 
            "label": "DINO"
        }, 
        {
            "default": false, 
            "enabled": true, 
            "properties": null, 
            "label": "DRTO"
        }, 
        {
            "default": false, 
            "enabled": true, 
            "properties": null, 
            "label": "EBLA"
        }, 
        {
            "default": false, 
            "enabled": true, 
            "properties": null, 
            "label": "EDAL"
        }, 
        {
            "default": false, 
            "enabled": true, 
            "properties": null, 
            "label": "EDIS"
        }, 
        {
            "default": false, 
            "enabled": true, 
            "properties": null, 
            "label": "EFMO"
        }, 
        {
            "default": false, 
            "enabled": true, 
            "properties": null, 
            "label": "EISE"
        }, 
        {
            "default": false, 
            "enabled": true, 
            "properties": null, 
            "label": "ELMA"
        }, 
        {
            "default": false, 
            "enabled": true, 
            "properties": null, 
            "label": "ELMO"
        }, 
        {
            "default": false, 
            "enabled": true, 
            "properties": null, 
            "label": "ELRO"
        }, 
        {
            "default": false, 
            "enabled": true, 
            "properties": null, 
            "label": "EUON"
        }, 
        {
            "default": false, 
            "enabled": true, 
            "properties": null, 
            "label": "EVER"
        }, 
        {
            "default": false, 
            "enabled": true, 
            "properties": null, 
            "label": "FEHA"
        }, 
        {
            "default": false, 
            "enabled": true, 
            "properties": null, 
            "label": "FIIS"
        }, 
        {
            "default": false, 
            "enabled": true, 
            "properties": null, 
            "label": "FILA"
        }, 
        {
            "default": false, 
            "enabled": true, 
            "properties": null, 
            "label": "FLFO"
        }, 
        {
            "default": false, 
            "enabled": true, 
            "properties": null, 
            "label": "FLNI"
        }, 
        {
            "default": false, 
            "enabled": true, 
            "properties": null, 
            "label": "FOBO"
        }, 
        {
            "default": false, 
            "enabled": true, 
            "properties": null, 
            "label": "FOBU"
        }, 
        {
            "default": false, 
            "enabled": true, 
            "properties": null, 
            "label": "FOCA"
        }, 
        {
            "default": false, 
            "enabled": true, 
            "properties": null, 
            "label": "FODA"
        }, 
        {
            "default": false, 
            "enabled": true, 
            "properties": null, 
            "label": "FODO"
        }, 
        {
            "default": false, 
            "enabled": true, 
            "properties": null, 
            "label": "FODU"
        }, 
        {
            "default": false, 
            "enabled": true, 
            "properties": null, 
            "label": "FOFO"
        }, 
        {
            "default": false, 
            "enabled": true, 
            "properties": null, 
            "label": "FOFR"
        }, 
        {
            "default": false, 
            "enabled": true, 
            "properties": null, 
            "label": "FOLA"
        }, 
        {
            "default": false, 
            "enabled": true, 
            "properties": null, 
            "label": "FOLS"
        }, 
        {
            "default": false, 
            "enabled": true, 
            "properties": null, 
            "label": "FOMA"
        }, 
        {
            "default": false, 
            "enabled": true, 
            "properties": null, 
            "label": "FOMC"
        }, 
        {
            "default": false, 
            "enabled": true, 
            "properties": null, 
            "label": "FONE"
        }, 
        {
            "default": false, 
            "enabled": true, 
            "properties": null, 
            "label": "FOPO"
        }, 
        {
            "default": false, 
            "enabled": true, 
            "properties": null, 
            "label": "FOPU"
        }, 
        {
            "default": false, 
            "enabled": true, 
            "properties": null, 
            "label": "FORA"
        }, 
        {
            "default": false, 
            "enabled": true, 
            "properties": null, 
            "label": "FOSC"
        }, 
        {
            "default": false, 
            "enabled": true, 
            "properties": null, 
            "label": "FOSM"
        }, 
        {
            "default": false, 
            "enabled": true, 
            "properties": null, 
            "label": "FOST"
        }, 
        {
            "default": false, 
            "enabled": true, 
            "properties": null, 
            "label": "FOSU"
        }, 
        {
            "default": false, 
            "enabled": true, 
            "properties": null, 
            "label": "FOTH"
        }, 
        {
            "default": false, 
            "enabled": true, 
            "properties": null, 
            "label": "FOUN"
        }, 
        {
            "default": false, 
            "enabled": true, 
            "properties": null, 
            "label": "FOUS"
        }, 
        {
            "default": false, 
            "enabled": true, 
            "properties": null, 
            "label": "FOVA"
        }, 
        {
            "default": false, 
            "enabled": true, 
            "properties": null, 
            "label": "FOWA"
        }, 
        {
            "default": false, 
            "enabled": true, 
            "properties": null, 
            "label": "FRDE"
        }, 
        {
            "default": false, 
            "enabled": true, 
            "properties": null, 
            "label": "FRDO"
        }, 
        {
            "default": false, 
            "enabled": true, 
            "properties": null, 
            "label": "FRHI"
        }, 
        {
            "default": false, 
            "enabled": true, 
            "properties": null, 
            "label": "FRLA"
        }, 
        {
            "default": false, 
            "enabled": true, 
            "properties": null, 
            "label": "FRSP"
        }, 
        {
            "default": false, 
            "enabled": true, 
            "properties": null, 
            "label": "GAAR"
        }, 
        {
            "default": false, 
            "enabled": true, 
            "properties": null, 
            "label": "GARI"
        }, 
        {
            "default": false, 
            "enabled": true, 
            "properties": null, 
            "label": "GATE"
        }, 
        {
            "default": false, 
            "enabled": true, 
            "properties": null, 
            "label": "GEGR"
        }, 
        {
            "default": false, 
            "enabled": true, 
            "properties": null, 
            "label": "GERO"
        }, 
        {
            "default": false, 
            "enabled": true, 
            "properties": null, 
            "label": "GETT"
        }, 
        {
            "default": false, 
            "enabled": true, 
            "properties": null, 
            "label": "GEWA"
        }, 
        {
            "default": false, 
            "enabled": true, 
            "properties": null, 
            "label": "GICL"
        }, 
        {
            "default": false, 
            "enabled": true, 
            "properties": null, 
            "label": "GLAC"
        }, 
        {
            "default": false, 
            "enabled": true, 
            "properties": null, 
            "label": "GLBA"
        }, 
        {
            "default": false, 
            "enabled": true, 
            "properties": null, 
            "label": "GLCA"
        }, 
        {
            "default": false, 
            "enabled": true, 
            "properties": null, 
            "label": "GLDE"
        }, 
        {
            "default": false, 
            "enabled": true, 
            "properties": null, 
            "label": "GOGA"
        }, 
        {
            "default": false, 
            "enabled": true, 
            "properties": null, 
            "label": "GOIS"
        }, 
        {
            "default": false, 
            "enabled": true, 
            "properties": null, 
            "label": "GOSP"
        }, 
        {
            "default": false, 
            "enabled": true, 
            "properties": null, 
            "label": "GRBA"
        }, 
        {
            "default": false, 
            "enabled": true, 
            "properties": null, 
            "label": "GRCA"
        }, 
        {
            "default": false, 
            "enabled": true, 
            "properties": null, 
            "label": "GREE"
        }, 
        {
            "default": false, 
            "enabled": true, 
            "properties": null, 
            "label": "GREG"
        }, 
        {
            "default": false, 
            "enabled": true, 
            "properties": null, 
            "label": "GRKO"
        }, 
        {
            "default": false, 
            "enabled": true, 
            "properties": null, 
            "label": "GRPO"
        }, 
        {
            "default": false, 
            "enabled": true, 
            "properties": null, 
            "label": "GRSA"
        }, 
        {
            "default": false, 
            "enabled": true, 
            "properties": null, 
            "label": "GRSM"
        }, 
        {
            "default": false, 
            "enabled": true, 
            "properties": null, 
            "label": "GRSP"
        }, 
        {
            "default": false, 
            "enabled": true, 
            "properties": null, 
            "label": "GRTE"
        }, 
        {
            "default": false, 
            "enabled": true, 
            "properties": null, 
            "label": "GUCO"
        }, 
        {
            "default": false, 
            "enabled": true, 
            "properties": null, 
            "label": "GUIS"
        }, 
        {
            "default": false, 
            "enabled": true, 
            "properties": null, 
            "label": "GUMO"
        }, 
        {
            "default": false, 
            "enabled": true, 
            "properties": null, 
            "label": "GWCA"
        }, 
        {
            "default": false, 
            "enabled": true, 
            "properties": null, 
            "label": "GWMP"
        }, 
        {
            "default": false, 
            "enabled": true, 
            "properties": null, 
            "label": "HAFE"
        }, 
        {
            "default": false, 
            "enabled": true, 
            "properties": null, 
            "label": "HAFO"
        }, 
        {
            "default": false, 
            "enabled": true, 
            "properties": null, 
            "label": "HAGR"
        }, 
        {
            "default": false, 
            "enabled": true, 
            "properties": null, 
            "label": "HAHA"
        }, 
        {
            "default": false, 
            "enabled": true, 
            "properties": null, 
            "label": "HALE"
        }, 
        {
            "default": false, 
            "enabled": true, 
            "properties": null, 
            "label": "HAMP"
        }, 
        {
            "default": false, 
            "enabled": true, 
            "properties": null, 
            "label": "HAVO"
        }, 
        {
            "default": false, 
            "enabled": true, 
            "properties": null, 
            "label": "HEHO"
        }, 
        {
            "default": false, 
            "enabled": true, 
            "properties": null, 
            "label": "HOBE"
        }, 
        {
            "default": false, 
            "enabled": true, 
            "properties": null, 
            "label": "HOCU"
        }, 
        {
            "default": false, 
            "enabled": true, 
            "properties": null, 
            "label": "HOFR"
        }, 
        {
            "default": false, 
            "enabled": true, 
            "properties": null, 
            "label": "HOFU"
        }, 
        {
            "default": false, 
            "enabled": true, 
            "properties": null, 
            "label": "HOME"
        }, 
        {
            "default": false, 
            "enabled": true, 
            "properties": null, 
            "label": "HOSP"
        }, 
        {
            "default": false, 
            "enabled": true, 
            "properties": null, 
            "label": "HOVE"
        }, 
        {
            "default": false, 
            "enabled": true, 
            "properties": null, 
            "label": "HSTR"
        }, 
        {
            "default": false, 
            "enabled": true, 
            "properties": null, 
            "label": "HUTR"
        }, 
        {
            "default": false, 
            "enabled": true, 
            "properties": null, 
            "label": "IATR"
        }, 
        {
            "default": false, 
            "enabled": true, 
            "properties": null, 
            "label": "ILMI"
        }, 
        {
            "default": false, 
            "enabled": true, 
            "properties": null, 
            "label": "INDE"
        }, 
        {
            "default": false, 
            "enabled": true, 
            "properties": null, 
            "label": "INDU"
        }, 
        {
            "default": false, 
            "enabled": true, 
            "properties": null, 
            "label": "ISRO"
        }, 
        {
            "default": false, 
            "enabled": true, 
            "properties": null, 
            "label": "JAGA"
        }, 
        {
            "default": false, 
            "enabled": true, 
            "properties": null, 
            "label": "JAZZ"
        }, 
        {
            "default": false, 
            "enabled": true, 
            "properties": null, 
            "label": "JECA"
        }, 
        {
            "default": false, 
            "enabled": true, 
            "properties": null, 
            "label": "JEFF"
        }, 
        {
            "default": false, 
            "enabled": true, 
            "properties": null, 
            "label": "JELA"
        }, 
        {
            "default": false, 
            "enabled": true, 
            "properties": null, 
            "label": "JICA"
        }, 
        {
            "default": false, 
            "enabled": true, 
            "properties": null, 
            "label": "JODA"
        }, 
        {
            "default": false, 
            "enabled": true, 
            "properties": null, 
            "label": "JODR"
        }, 
        {
            "default": false, 
            "enabled": true, 
            "properties": null, 
            "label": "JOFI"
        }, 
        {
            "default": false, 
            "enabled": true, 
            "properties": null, 
            "label": "JOFL"
        }, 
        {
            "default": false, 
            "enabled": true, 
            "properties": null, 
            "label": "JOMU"
        }, 
        {
            "default": false, 
            "enabled": true, 
            "properties": null, 
            "label": "JOTR"
        }, 
        {
            "default": false, 
            "enabled": true, 
            "properties": null, 
            "label": "KAHO"
        }, 
        {
            "default": false, 
            "enabled": true, 
            "properties": null, 
            "label": "KALA"
        }, 
        {
            "default": false, 
            "enabled": true, 
            "properties": null, 
            "label": "KATM"
        }, 
        {
            "default": false, 
            "enabled": true, 
            "properties": null, 
            "label": "KEAQ"
        }, 
        {
            "default": false, 
            "enabled": true, 
            "properties": null, 
            "label": "KEFJ"
        }, 
        {
            "default": false, 
            "enabled": true, 
            "properties": null, 
            "label": "KEMO"
        }, 
        {
            "default": false, 
            "enabled": true, 
            "properties": null, 
            "label": "KEWE"
        }, 
        {
            "default": false, 
            "enabled": true, 
            "properties": null, 
            "label": "KICA"
        }, 
        {
            "default": false, 
            "enabled": true, 
            "properties": null, 
            "label": "KIMO"
        }, 
        {
            "default": false, 
            "enabled": true, 
            "properties": null, 
            "label": "KLGO"
        }, 
        {
            "default": false, 
            "enabled": true, 
            "properties": null, 
            "label": "KNRI"
        }, 
        {
            "default": false, 
            "enabled": true, 
            "properties": null, 
            "label": "KOVA"
        }, 
        {
            "default": false, 
            "enabled": true, 
            "properties": null, 
            "label": "KOWA"
        }, 
        {
            "default": false, 
            "enabled": true, 
            "properties": null, 
            "label": "LABE"
        }, 
        {
            "default": false, 
            "enabled": true, 
            "properties": null, 
            "label": "LACH"
        }, 
        {
            "default": false, 
            "enabled": true, 
            "properties": null, 
            "label": "LACL"
        }, 
        {
            "default": false, 
            "enabled": true, 
            "properties": null, 
            "label": "LAMR"
        }, 
        {
            "default": false, 
            "enabled": true, 
            "properties": null, 
            "label": "LARO"
        }, 
        {
            "default": false, 
            "enabled": true, 
            "properties": null, 
            "label": "LAVO"
        }, 
        {
            "default": false, 
            "enabled": true, 
            "properties": null, 
            "label": "LECL"
        }, 
        {
            "default": false, 
            "enabled": true, 
            "properties": null, 
            "label": "LEWI"
        }, 
        {
            "default": false, 
            "enabled": true, 
            "properties": null, 
            "label": "LIBI"
        }, 
        {
            "default": false, 
            "enabled": true, 
            "properties": null, 
            "label": "LIBO"
        }, 
        {
            "default": false, 
            "enabled": true, 
            "properties": null, 
            "label": "LIHO"
        }, 
        {
            "default": false, 
            "enabled": true, 
            "properties": null, 
            "label": "LINC"
        }, 
        {
            "default": false, 
            "enabled": true, 
            "properties": null, 
            "label": "LIRI"
        }, 
        {
            "default": false, 
            "enabled": true, 
            "properties": null, 
            "label": "LONG"
        }, 
        {
            "default": false, 
            "enabled": true, 
            "properties": null, 
            "label": "LOWE"
        }, 
        {
            "default": false, 
            "enabled": true, 
            "properties": null, 
            "label": "LYBA"
        }, 
        {
            "default": false, 
            "enabled": true, 
            "properties": null, 
            "label": "LYJO"
        }, 
        {
            "default": false, 
            "enabled": true, 
            "properties": null, 
            "label": "MABI"
        }, 
        {
            "default": false, 
            "enabled": true, 
            "properties": null, 
            "label": "MACA"
        }, 
        {
            "default": false, 
            "enabled": true, 
            "properties": null, 
            "label": "MALU"
        }, 
        {
            "default": false, 
            "enabled": true, 
            "properties": null, 
            "label": "MAMC"
        }, 
        {
            "default": false, 
            "enabled": true, 
            "properties": null, 
            "label": "MANA"
        }, 
        {
            "default": false, 
            "enabled": true, 
            "properties": null, 
            "label": "MANZ"
        }, 
        {
            "default": false, 
            "enabled": true, 
            "properties": null, 
            "label": "MAVA"
        }, 
        {
            "default": false, 
            "enabled": true, 
            "properties": null, 
            "label": "MAWA"
        }, 
        {
            "default": false, 
            "enabled": true, 
            "properties": null, 
            "label": "MEHI"
        }, 
        {
            "default": false, 
            "enabled": true, 
            "properties": null, 
            "label": "MEVE"
        }, 
        {
            "default": false, 
            "enabled": true, 
            "properties": null, 
            "label": "MIIN"
        }, 
        {
            "default": false, 
            "enabled": true, 
            "properties": null, 
            "label": "MIMA"
        }, 
        {
            "default": false, 
            "enabled": true, 
            "properties": null, 
            "label": "MIMI"
        }, 
        {
            "default": false, 
            "enabled": true, 
            "properties": null, 
            "label": "MISS"
        }, 
        {
            "default": false, 
            "enabled": true, 
            "properties": null, 
            "label": "MNRR"
        }, 
        {
            "default": false, 
            "enabled": true, 
            "properties": null, 
            "label": "MOCA"
        }, 
        {
            "default": false, 
            "enabled": true, 
            "properties": null, 
            "label": "MOCR"
        }, 
        {
            "default": false, 
            "enabled": true, 
            "properties": null, 
            "label": "MOJA"
        }, 
        {
            "default": false, 
            "enabled": true, 
            "properties": null, 
            "label": "MONO"
        }, 
        {
            "default": false, 
            "enabled": true, 
            "properties": null, 
            "label": "MORA"
        }, 
        {
            "default": false, 
            "enabled": true, 
            "properties": null, 
            "label": "MORR"
        }, 
        {
            "default": false, 
            "enabled": true, 
            "properties": null, 
            "label": "MORU"
        }, 
        {
            "default": false, 
            "enabled": true, 
            "properties": null, 
            "label": "MUWO"
        }, 
        {
            "default": false, 
            "enabled": true, 
            "properties": null, 
            "label": "NABR"
        }, 
        {
            "default": false, 
            "enabled": true, 
            "properties": null, 
            "label": "NACE"
        }, 
        {
            "default": false, 
            "enabled": true, 
            "properties": null, 
            "label": "NAMA"
        }, 
        {
            "default": false, 
            "enabled": true, 
            "properties": null, 
            "label": "NATC"
        }, 
        {
            "default": false, 
            "enabled": true, 
            "properties": null, 
            "label": "NATR"
        }, 
        {
            "default": false, 
            "enabled": true, 
            "properties": null, 
            "label": "NAVA"
        }, 
        {
            "default": false, 
            "enabled": true, 
            "properties": null, 
            "label": "NEBE"
        }, 
        {
            "default": false, 
            "enabled": true, 
            "properties": null, 
            "label": "NEPE"
        }, 
        {
            "default": false, 
            "enabled": true, 
            "properties": null, 
            "label": "NERI"
        }, 
        {
            "default": false, 
            "enabled": true, 
            "properties": null, 
            "label": "NICO"
        }, 
        {
            "default": false, 
            "enabled": true, 
            "properties": null, 
            "label": "NIOB"
        }, 
        {
            "default": false, 
            "enabled": true, 
            "properties": null, 
            "label": "NISI"
        }, 
        {
            "default": false, 
            "enabled": true, 
            "properties": null, 
            "label": "NOAT"
        }, 
        {
            "default": false, 
            "enabled": true, 
            "properties": null, 
            "label": "NOCA"
        }, 
        {
            "default": false, 
            "enabled": true, 
            "properties": null, 
            "label": "NPSA"
        }, 
        {
            "default": false, 
            "enabled": true, 
            "properties": null, 
            "label": "NWWM"
        }, 
        {
            "default": false, 
            "enabled": true, 
            "properties": null, 
            "label": "OBED"
        }, 
        {
            "default": false, 
            "enabled": true, 
            "properties": null, 
            "label": "OCMU"
        }, 
        {
            "default": false, 
            "enabled": true, 
            "properties": null, 
            "label": "OLST"
        }, 
        {
            "default": false, 
            "enabled": true, 
            "properties": null, 
            "label": "OLYM"
        }, 
        {
            "default": false, 
            "enabled": true, 
            "properties": null, 
            "label": "ORCA"
        }, 
        {
            "default": false, 
            "enabled": true, 
            "properties": null, 
            "label": "ORPI"
        }, 
        {
            "default": false, 
            "enabled": true, 
            "properties": null, 
            "label": "OXHI"
        }, 
        {
            "default": false, 
            "enabled": true, 
            "properties": null, 
            "label": "OZAR"
        }, 
        {
            "default": false, 
            "enabled": true, 
            "properties": null, 
            "label": "PAAL"
        }, 
        {
            "default": false, 
            "enabled": true, 
            "properties": null, 
            "label": "PAAV"
        }, 
        {
            "default": false, 
            "enabled": true, 
            "properties": null, 
            "label": "PAIS"
        }, 
        {
            "default": false, 
            "enabled": true, 
            "properties": null, 
            "label": "PECO"
        }, 
        {
            "default": false, 
            "enabled": true, 
            "properties": null, 
            "label": "PEFO"
        }, 
        {
            "default": false, 
            "enabled": true, 
            "properties": null, 
            "label": "PERI"
        }, 
        {
            "default": false, 
            "enabled": true, 
            "properties": null, 
            "label": "PETE"
        }, 
        {
            "default": false, 
            "enabled": true, 
            "properties": null, 
            "label": "PETR"
        }, 
        {
            "default": false, 
            "enabled": true, 
            "properties": null, 
            "label": "PEVI"
        }, 
        {
            "default": false, 
            "enabled": true, 
            "properties": null, 
            "label": "PIMA"
        }, 
        {
            "default": false, 
            "enabled": true, 
            "properties": null, 
            "label": "PINN"
        }, 
        {
            "default": false, 
            "enabled": true, 
            "properties": null, 
            "label": "PIPE"
        }, 
        {
            "default": false, 
            "enabled": true, 
            "properties": null, 
            "label": "PIRO"
        }, 
        {
            "default": false, 
            "enabled": true, 
            "properties": null, 
            "label": "PISC"
        }, 
        {
            "default": false, 
            "enabled": true, 
            "properties": null, 
            "label": "PISP"
        }, 
        {
            "default": false, 
            "enabled": true, 
            "properties": null, 
            "label": "POCH"
        }, 
        {
            "default": false, 
            "enabled": true, 
            "properties": null, 
            "label": "POHE"
        }, 
        {
            "default": false, 
            "enabled": true, 
            "properties": null, 
            "label": "POPO"
        }, 
        {
            "default": false, 
            "enabled": true, 
            "properties": null, 
            "label": "PORE"
        }, 
        {
            "default": false, 
            "enabled": true, 
            "properties": null, 
            "label": "PRSF"
        }, 
        {
            "default": false, 
            "enabled": true, 
            "properties": null, 
            "label": "PRWI"
        }, 
        {
            "default": false, 
            "enabled": true, 
            "properties": null, 
            "label": "PUHE"
        }, 
        {
            "default": false, 
            "enabled": true, 
            "properties": null, 
            "label": "PUHO"
        }, 
        {
            "default": false, 
            "enabled": true, 
            "properties": null, 
            "label": "RABR"
        }, 
        {
            "default": false, 
            "enabled": true, 
            "properties": null, 
            "label": "REDW"
        }, 
        {
            "default": false, 
            "enabled": true, 
            "properties": null, 
            "label": "RICH"
        }, 
        {
            "default": false, 
            "enabled": true, 
            "properties": null, 
            "label": "RIGR"
        }, 
        {
            "default": false, 
            "enabled": true, 
            "properties": null, 
            "label": "ROCR"
        }, 
        {
            "default": false, 
            "enabled": true, 
            "properties": null, 
            "label": "ROLA"
        }, 
        {
            "default": false, 
            "enabled": true, 
            "properties": null, 
            "label": "ROMO"
        }, 
        {
            "default": false, 
            "enabled": true, 
            "properties": null, 
            "label": "RORI"
        }, 
        {
            "default": false, 
            "enabled": true, 
            "properties": null, 
            "label": "ROWI"
        }, 
        {
            "default": false, 
            "enabled": true, 
            "properties": null, 
            "label": "RUCA"
        }, 
        {
            "default": false, 
            "enabled": true, 
            "properties": null, 
            "label": "SAAN"
        }, 
        {
            "default": false, 
            "enabled": true, 
            "properties": null, 
            "label": "SACN"
        }, 
        {
            "default": false, 
            "enabled": true, 
            "properties": null, 
            "label": "SACR"
        }, 
        {
            "default": false, 
            "enabled": true, 
            "properties": null, 
            "label": "SAFR"
        }, 
        {
            "default": false, 
            "enabled": true, 
            "properties": null, 
            "label": "SAGA"
        }, 
        {
            "default": false, 
            "enabled": true, 
            "properties": null, 
            "label": "SAGU"
        }, 
        {
            "default": false, 
            "enabled": true, 
            "properties": null, 
            "label": "SAHI"
        }, 
        {
            "default": false, 
            "enabled": true, 
            "properties": null, 
            "label": "SAIR"
        }, 
        {
            "default": false, 
            "enabled": true, 
            "properties": null, 
            "label": "SAJH"
        }, 
        {
            "default": false, 
            "enabled": true, 
            "properties": null, 
            "label": "SAJU"
        }, 
        {
            "default": false, 
            "enabled": true, 
            "properties": null, 
            "label": "SAMA"
        }, 
        {
            "default": false, 
            "enabled": true, 
            "properties": null, 
            "label": "SAMO"
        }, 
        {
            "default": false, 
            "enabled": true, 
            "properties": null, 
            "label": "SAND"
        }, 
        {
            "default": false, 
            "enabled": true, 
            "properties": null, 
            "label": "SAPA"
        }, 
        {
            "default": false, 
            "enabled": true, 
            "properties": null, 
            "label": "SAPU"
        }, 
        {
            "default": false, 
            "enabled": true, 
            "properties": null, 
            "label": "SARA"
        }, 
        {
            "default": false, 
            "enabled": true, 
            "properties": null, 
            "label": "SARI"
        }, 
        {
            "default": false, 
            "enabled": true, 
            "properties": null, 
            "label": "SCBL"
        }, 
        {
            "default": false, 
            "enabled": true, 
            "properties": null, 
            "label": "SEKI"
        }, 
        {
            "default": false, 
            "enabled": true, 
            "properties": null, 
            "label": "SHEN"
        }, 
        {
            "default": false, 
            "enabled": true, 
            "properties": null, 
            "label": "SHIL"
        }, 
        {
            "default": false, 
            "enabled": true, 
            "properties": null, 
            "label": "SITK"
        }, 
        {
            "default": false, 
            "enabled": true, 
            "properties": null, 
            "label": "SLBE"
        }, 
        {
            "default": false, 
            "enabled": true, 
            "properties": null, 
            "label": "SPAR"
        }, 
        {
            "default": false, 
            "enabled": true, 
            "properties": null, 
            "label": "STEA"
        }, 
        {
            "default": false, 
            "enabled": true, 
            "properties": null, 
            "label": "STLI"
        }, 
        {
            "default": false, 
            "enabled": true, 
            "properties": null, 
            "label": "STRI"
        }, 
        {
            "default": false, 
            "enabled": true, 
            "properties": null, 
            "label": "SUCR"
        }, 
        {
            "default": false, 
            "enabled": true, 
            "properties": null, 
            "label": "TAPR"
        }, 
        {
            "default": false, 
            "enabled": true, 
            "properties": null, 
            "label": "THIS"
        }, 
        {
            "default": false, 
            "enabled": true, 
            "properties": null, 
            "label": "THJE"
        }, 
        {
            "default": false, 
            "enabled": true, 
            "properties": null, 
            "label": "THKO"
        }, 
        {
            "default": false, 
            "enabled": true, 
            "properties": null, 
            "label": "THRB"
        }, 
        {
            "default": false, 
            "enabled": true, 
            "properties": null, 
            "label": "THRI"
        }, 
        {
            "default": false, 
            "enabled": true, 
            "properties": null, 
            "label": "THRO"
        }, 
        {
            "default": false, 
            "enabled": true, 
            "properties": null, 
            "label": "THST"
        }, 
        {
            "default": false, 
            "enabled": true, 
            "properties": null, 
            "label": "TICA"
        }, 
        {
            "default": false, 
            "enabled": true, 
            "properties": null, 
            "label": "TIMU"
        }, 
        {
            "default": false, 
            "enabled": true, 
            "properties": null, 
            "label": "TONT"
        }, 
        {
            "default": false, 
            "enabled": true, 
            "properties": null, 
            "label": "TUAI"
        }, 
        {
            "default": false, 
            "enabled": true, 
            "properties": null, 
            "label": "TUIN"
        }, 
        {
            "default": false, 
            "enabled": true, 
            "properties": null, 
            "label": "TUMA"
        }, 
        {
            "default": false, 
            "enabled": true, 
            "properties": null, 
            "label": "TUPE"
        }, 
        {
            "default": false, 
            "enabled": true, 
            "properties": null, 
            "label": "TUZI"
        }, 
        {
            "default": false, 
            "enabled": true, 
            "properties": null, 
            "label": "ULSG"
        }, 
        {
            "default": false, 
            "enabled": true, 
            "properties": null, 
            "label": "UPDE"
        }, 
        {
            "default": false, 
            "enabled": true, 
            "properties": null, 
            "label": "VAFO"
        }, 
        {
            "default": false, 
            "enabled": true, 
            "properties": null, 
            "label": "VALR"
        }, 
        {
            "default": false, 
            "enabled": true, 
            "properties": null, 
            "label": "VAMA"
        }, 
        {
            "default": false, 
            "enabled": true, 
            "properties": null, 
            "label": "VICK"
        }, 
        {
            "default": false, 
            "enabled": true, 
            "properties": null, 
            "label": "VICR"
        }, 
        {
            "default": false, 
            "enabled": true, 
            "properties": null, 
            "label": "VIIS"
        }, 
        {
            "default": false, 
            "enabled": true, 
            "properties": null, 
            "label": "VIVE"
        }, 
        {
            "default": false, 
            "enabled": true, 
            "properties": null, 
            "label": "VOYA"
        }, 
        {
            "default": false, 
            "enabled": true, 
            "properties": null, 
            "label": "WABA"
        }, 
        {
            "default": false, 
            "enabled": true, 
            "properties": null, 
            "label": "WACA"
        }, 
        {
            "default": false, 
            "enabled": true, 
            "properties": null, 
            "label": "WAMO"
        }, 
        {
            "default": false, 
            "enabled": true, 
            "properties": null, 
            "label": "WAPA"
        }, 
        {
            "default": false, 
            "enabled": true, 
            "properties": null, 
            "label": "WEFA"
        }, 
        {
            "default": false, 
            "enabled": true, 
            "properties": null, 
            "label": "WHHO"
        }, 
        {
            "default": false, 
            "enabled": true, 
            "properties": null, 
            "label": "WHIS"
        }, 
        {
            "default": false, 
            "enabled": true, 
            "properties": null, 
            "label": "WHMI"
        }, 
        {
            "default": false, 
            "enabled": true, 
            "properties": null, 
            "label": "WHSA"
        }, 
        {
            "default": false, 
            "enabled": true, 
            "properties": null, 
            "label": "WICA"
        }, 
        {
            "default": false, 
            "enabled": true, 
            "properties": null, 
            "label": "WICR"
        }, 
        {
            "default": false, 
            "enabled": true, 
            "properties": null, 
            "label": "WIHO"
        }, 
        {
            "default": false, 
            "enabled": true, 
            "properties": null, 
            "label": "WORI"
        }, 
        {
            "default": false, 
            "enabled": true, 
            "properties": null, 
            "label": "WOTR"
        }, 
        {
            "default": false, 
            "enabled": true, 
            "properties": null, 
            "label": "WRBR"
        }, 
        {
            "default": false, 
            "enabled": true, 
            "properties": null, 
            "label": "WRST"
        }, 
        {
            "default": false, 
            "enabled": true, 
            "properties": null, 
            "label": "WUPA"
        }, 
        {
            "default": false, 
            "enabled": true, 
            "properties": null, 
            "label": "YELL"
        }, 
        {
            "default": false, 
            "enabled": true, 
            "properties": null, 
            "label": "YOSE"
        }, 
        {
            "default": false, 
            "enabled": true, 
            "properties": null, 
            "label": "YUCH"
        }, 
        {
            "default": false, 
            "enabled": true, 
            "properties": null, 
            "label": "YUHO"
        }, 
        {
            "default": false, 
            "enabled": true, 
            "properties": null, 
            "label": "ZION"
        }
    ], 
    "tooltip": "", 
    "input_type": "select", 
    "placeholder": ""
}